{"images": [{"imgurl": "http://localhost:9000/images/00_00_00_27.png", "imgclass": "fish"}, {"imgurl": "http://localhost:9000/images/00_00_02_21.png", "imgclass": "derp"}, {"imgurl": "http://localhost:9000/images/00_00_24_10.png", "imgclass": "shell"}, {"imgurl": "http://localhost:9000/images/00_03_45_14.png", "imgclass": "fish"}, {"imgurl": "http://localhost:9000/images/00_03_46_22.png", "imgclass": "fish"}, {"imgurl": "http://localhost:9000/images/00_04_36_09.png", "imgclass": "crab"}, {"imgurl": "http://localhost:9000/images/00_05_17_24.png", "imgclass": "fish"}, {"imgurl": "http://localhost:9000/images/00_06_42_29.png", "imgclass": "shell"}, {"imgurl": "http://localhost:9000/images/00_06_45_18.png", "imgclass": "fish"}, {"imgurl": "http://localhost:9000/images/00_08_58_13.png", "imgclass": "crab"}, {"imgurl": "http://localhost:9000/images/00_10_03_23.png", "imgclass": "shell"}, {"imgurl": "http://localhost:9000/images/00_11_46_16.png", "imgclass": "crab"}, {"imgurl": "http://localhost:9000/images/00_14_27_06.png", "imgclass": "crab"}, {"imgurl": "http://localhost:9000/images/00_15_42_13.png", "imgclass": "shell"}, {"imgurl": "http://localhost:9000/images/00_15_55_14.png", "imgclass": "fish"}, {"imgurl": "http://localhost:9000/images/00_16_37_06.png", "imgclass": "crab"}, {"imgurl": "http://localhost:9000/images/00_17_06_03.png", "imgclass": "shell"}, {"imgurl": "http://localhost:9000/images/00_17_59_17.png", "imgclass": "fish"}, {"imgurl": "http://localhost:9000/images/00_18_27_16.png", "imgclass": "crab"}, {"imgurl": "http://localhost:9000/images/00_18_31_03.png", "imgclass": "crab"}, {"imgurl": "http://localhost:9000/images/00_19_13_04.png", "imgclass": "shell"}, {"imgurl": "http://localhost:9000/images/00_22_26_19.png", "imgclass": "ray"}, {"imgurl": "http://localhost:9000/images/00_23_08_17.png", "imgclass": "crab"}, {"imgurl": "http://localhost:9000/images/07_21_46_18.png", "imgclass": "ray"}, {"imgurl": "http://localhost:9000/images/07_22_30_16.png", "imgclass": "shell"}, {"imgurl": "http://localhost:9000/images/07_22_49_17.png", "imgclass": "ray"}, {"imgurl": "http://localhost:9000/images/07_25_13_18.png", "imgclass": "shell"}, {"imgurl": "http://localhost:9000/images/07_31_51_14.png", "imgclass": "crab"}, {"imgurl": "http://localhost:9000/images/07_49_44_07.png", "imgclass": "ray"}, {"imgurl": "http://localhost:9000/images/07_56_19_12.png", "imgclass": "ray"}, {"imgurl": "http://localhost:9000/images/08080416.png", "imgclass": "ray"}, {"imgurl": "http://localhost:9000/images/08_02_34_15.png", "imgclass": "fish"}, {"imgurl": "http://localhost:9000/images/08_04_05_24.png", "imgclass": "fish"}, {"imgurl": "http://localhost:9000/images/08_09_10_00.png", "imgclass": "crab"}, {"imgurl": "http://localhost:9000/images/08_12_10_28.png", "imgclass": "crab"}, {"imgurl": "http://localhost:9000/images/08_16_10_02.png", "imgclass": "fish"}, {"imgurl": "http://localhost:9000/images/08_25_15_15.png", "imgclass": "shell"}, {"imgurl": "http://localhost:9000/images/08_27_28_23.png", "imgclass": "ray"}, {"imgurl": "http://localhost:9000/images/08_29_49_28.png", "imgclass": "crab"}, {"imgurl": "http://localhost:9000/images/08_31_37_01.png", "imgclass": "shell"}, {"imgurl": "http://localhost:9000/images/08_42_03_03.png", "imgclass": "shell"}, {"imgurl": "http://localhost:9000/images/08_43_14_28.png", "imgclass": "ray"}, {"imgurl": "http://localhost:9000/images/08_43_45_25.png", "imgclass": "ray"}, {"imgurl": "http://localhost:9000/images/08_51_00_17.png", "imgclass": "shell"}, {"imgurl": "http://localhost:9000/images/08_52_30_28.png", "imgclass": "ray"}, {"imgurl": "http://localhost:9000/images/08_53_05_20.png", "imgclass": "shell"}, {"imgurl": "http://localhost:9000/images/08_53_46_26.png", "imgclass": "shell"}, {"imgurl": "http://localhost:9000/images/08_56_29_21.png", "imgclass": "crab"}, {"imgurl": "http://localhost:9000/images/09_20_57_24.png", "imgclass": "fish"}, {"imgurl": "http://localhost:9000/images/09_28_21_24.png", "imgclass": "fish"}, {"imgurl": "http://localhost:9000/images/09_30_47_07.png", "imgclass": "fish"}, {"imgurl": "http://localhost:9000/images/09_40_46_11.png", "imgclass": "ray"}, {"imgurl": "http://localhost:9000/images/09_46_49_19.png", "imgclass": "fish"}, {"imgurl": "http://localhost:9000/images/09_49_03_05.png", "imgclass": "fish"}, {"imgurl": "http://localhost:9000/images/09_49_04_19.png", "imgclass": "crab"}, {"imgurl": "http://localhost:9000/images/10_14_14_00.png", "imgclass": "ray"}, {"imgurl": "http://localhost:9000/images/10_15_54_15.png", "imgclass": "shell"}, {"imgurl": "http://localhost:9000/images/10_22_58_28.png", "imgclass": "crab"}, {"imgurl": "http://localhost:9000/images/10_49_30_10.png", "imgclass": "crab"}, {"imgurl": "http://localhost:9000/images/11_45_21_00.png", "imgclass": "ray"}, {"imgurl": "http://localhost:9000/images/12_33_23_06.png", "imgclass": "fish"}, {"imgurl": "http://localhost:9000/images/12_34_28_12.png", "imgclass": "crab"}, {"imgurl": "http://localhost:9000/images/13_29_30_10.png", "imgclass": "shell"}, {"imgurl": "http://localhost:9000/images/14_09_48_10.png", "imgclass": "shell"}, {"imgurl": "http://localhost:9000/images/16_43_19_16.png", "imgclass": "ray"}, {"imgurl": "http://localhost:9000/images/18_33_38_17.png", "imgclass": "crab"}, {"imgurl": "http://localhost:9000/images/21_14_30_15.png", "imgclass": "fish"}, {"imgurl": "http://localhost:9000/images/21_43_31_09.png", "imgclass": "ray"}, {"imgurl": "http://localhost:9000/images/22_02_59_05.png", "imgclass": "shell"}, {"imgurl": "http://localhost:9000/images/22_17_09_10.png", "imgclass": "ray"}, {"imgurl": "http://localhost:9000/images/22_33_18_26.png", "imgclass": "fish"}]}